omnibot/__init__.py
omnibot/app.py
omnibot/processor.py
omnibot/settings.py
omnibot/setup_logging.py
omnibot/watcher.py
omnibot/webhook_worker.py
omnibot/wsgi.py
omnibot/authnz/__init__.py
omnibot/authnz/envoy_checks.py
omnibot/callbacks/__init__.py
omnibot/callbacks/interactive_component_callbacks.py
omnibot/callbacks/message_callbacks.py
omnibot/callbacks/network_callbacks.py
omnibot/callbacks/slash_command_callbacks.py
omnibot/routes/__init__.py
omnibot/routes/api.py
omnibot/scripts/__init__.py
omnibot/scripts/omniredis.py
omnibot/scripts/utils.py
omnibot/services/__init__.py
omnibot/services/omniredis.py
omnibot/services/sqs.py
omnibot/services/stats.py
omnibot/services/slack/__init__.py
omnibot/services/slack/bot.py
omnibot/services/slack/interactive_component.py
omnibot/services/slack/message.py
omnibot/services/slack/parser.py
omnibot/services/slack/slash_command.py
omnibot/services/slack/team.py
omnibot/utils/__init__.py
omnibot/utils/settings.py
omnibot-1.0.3.dist-info/LICENSE
omnibot-1.0.3.dist-info/METADATA
omnibot-1.0.3.dist-info/NOTICE
omnibot-1.0.3.dist-info/WHEEL
omnibot-1.0.3.dist-info/top_level.txt
omnibot-1.0.3.dist-info/RECORD
